LICENSE
MANIFEST.in
README.md
pyproject.toml
requirements.txt
coffea_maker/__init__.py
coffea_maker.egg-info/PKG-INFO
coffea_maker.egg-info/SOURCES.txt
coffea_maker.egg-info/dependency_links.txt
coffea_maker.egg-info/top_level.txt