Metadata-Version: 2.1
Name: coffea-maker
Version: 0.1.0
Summary: Law automation for coffea-based workflows.
Author-email: Marcel Rieger <marcel.rieger@cern.ch>
License: Copyright (c) 2024, Marcel Rieger
Project-URL: Homepage, https://github.com/riga/scinum
Project-URL: Documentation, https://scinum.readthedocs.io
Project-URL: Repository, https://github.com/riga/scinum.git
Keywords: coffea,law
Classifier: Programming Language :: Python
Classifier: Programming Language :: Python :: 3
Classifier: Programming Language :: Python :: 3.8
Classifier: Programming Language :: Python :: 3.9
Classifier: Programming Language :: Python :: 3.10
Classifier: Programming Language :: Python :: 3.11
Classifier: Programming Language :: Python :: 3.12
Classifier: Development Status :: 5 - Production/Stable
Classifier: Operating System :: OS Independent
Classifier: License :: OSI Approved :: BSD License
Classifier: Intended Audience :: Developers
Classifier: Intended Audience :: Science/Research
Classifier: Intended Audience :: Information Technology
Requires-Python: >=3.8
License-File: LICENSE
